blink.v
module blink(input clk, output reg led);
  reg [2:0] count = 0;
  always @(posedge clk) begin
    count <= count + 1;
    led <= count[2];
  end
endmodule

module tb;
  reg clk = 0;
  wire led;
  blink dut(.clk(clk), .led(led));
  always #5 clk = ~clk;
  initial begin
    $dumpfile("blink.vcd");
    $dumpvars(0, tb);
    #100 $finish;
  end
endmodule

blink.vcd
$date
	Sat Aug 22 18:16:49 2026
$end
$version
	Icarus Verilog
$end
$timescale
	1s
$end
$scope module tb $end
$var wire 1 ! led $end
$var reg 1 " clk $end
$scope module dut $end
$var wire 1 " clk $end
$var reg 3 # count [2:0] $end
$var reg 1 ! led $end
$upscope $end
$upscope $end
$enddefinitions $end
$comment Show the parameter values. $end
$dumpall
$end
#0
$dumpvars
b0 #
0"
x!
$end
#5
0!
b1 #
1"
#10
0"
#15
b10 #
1"
#20
0"
#25
b11 #
1"
#30
0"
#35
b100 #
1"
#40
0"
#45
1!
b101 #
1"
#50
0"
#55
b110 #
1"
#60
0"
#65
b111 #
1"
#70
0"
#75
b0 #
1"
#80
0"
#85
0!
b1 #
1"
#90
0"
#95
b10 #
1"
